Lab_3/mux2to1.v
module mux2to1(w0,w1,s,f);
input w0,w1,s;
output f;
reg f;
always @(w0 or w1 or s)
f=s?w1:w0;
endmodule

Lab_3/mux2to1_tb.v
`timescale 1ns/1ns
`include "mux2to1.v"

module mux2to1_tb();
reg x1,x2,s;
wire f;

mux2to1 hey(x1,x2,s,f);
initial
begin
$dumpfile("mux2to1_tb.vcd");
$dumpvars(0,mux2to1_tb);

s=1'b0;x1=1'b0;x2=1'b0;
#20;
s=1'b0;x1=1'b0;x2=1'b1;
#20;
s=1'b0;x1=1'b1;x2=1'b0;
#20;
s=1'b0;x1=1'b1;x2=1'b1;
#20;
s=1'b1;x1=1'b0;x2=1'b0;
#20;
s=1'b1;x1=1'b0;x2=1'b1;
#20;
s=1'b1;x1=1'b1;x2=1'b0;
#20;
s=1'b1;x1=1'b1;x2=1'b1;
#20;
$display("test Complete");
end
endmodule

Lab_3/mux2to1_tb.vcd
$date
	Wed Aug 14 09:35:40 2024
$end
$version
	Icarus Verilog
$end
$timescale
	1ns
$end
$scope module mux2to1_tb $end
$var wire 1 ! f $end
$var reg 1 " s $end
$var reg 1 # x1 $end
$var reg 1 $ x2 $end
$scope module hey $end
$var wire 1 " s $end
$var wire 1 # w0 $end
$var wire 1 $ w1 $end
$var reg 1 ! f $end
$upscope $end
$upscope $end
$enddefinitions $end
#0
$dumpvars
0$
0#
0"
0!
$end
#20
1$
#40
1!
0$
1#
#60
1$
#80
0!
0$
0#
1"
#100
1!
1$
#120
0!
0$
1#
#140
1!
1$
