Lab_3/mux8to1.v
module mux8to1 (
    input wire [7:0] d,      
    input wire s0,           
    input wire s1,           
    input wire s2,           
    output reg f            
);


always @(d or s0 or s1 or s2)
begin
case ({s0,s1,s2})

	3'b000: 
	begin 
	f=d[0];
	end
	
	3'b001:
	begin
	f = d[1];  
	end
        3'b010: 
        
        begin
        f = d[2];  
        end 
        
        3'b011: 
        
        begin
        f = d[3];  
        end
        
        3'b100: 
        begin
        f = d[4];  
        end
        3'b101: 
        
        begin
        f = d[5];  
        end
        
        3'b110: 
        begin
        f = d[6]; 
        end
        
        
        3'b111: 
        begin
        f = d[7];
        end
        
        endcase
   end
   
   endmodule

Lab_3/mux8to1_tb.v
`timescale 1ns/1ns
`include "mux8to1.v"

module mux8to1_tb();
reg [7:0] d;
reg s0,s1,s2;

wire f;

mux8to1 func (
    .d(d),
    .s0(s0),
    .s1(s1),
    .s2(s2),
    .f(f)
);

initial begin

	$dumpfile("mux8to1_tb.vcd");
    $dumpvars(0, mux8to1_tb);
    
    d = 8'b00000000; s0 = 0; s1 = 0; s2 = 0; #20;
    d = 8'b00000001; s0 = 0; s1 = 0; s2 = 0; #20;
    d = 8'b00000010; s0 = 1; s1 = 0; s2 = 0; #20;
    d = 8'b00000100; s0 = 0; s1 = 1; s2 = 0; #20;
    d = 8'b00001000; s0 = 1; s1 = 1; s2 = 0; #20;
    d = 8'b00010000; s0 = 0; s1 = 0; s2 = 1; #20;
    d = 8'b00100000; s0 = 1; s1 = 0; s2 = 1; #20;
    d = 8'b01000000; s0 = 0; s1 = 1; s2 = 1; #20;
    d = 8'b10000000; s0 = 1; s1 = 1; s2 = 1; #20;

    $display("Test Complete");
end

endmodule

Lab_3/mux8to1_tb.vcd
$date
	Wed Aug 14 11:04:52 2024
$end
$version
	Icarus Verilog
$end
$timescale
	1ns
$end
$scope module mux8to1_tb $end
$var wire 1 ! f $end
$var reg 8 " d [7:0] $end
$var reg 1 # s0 $end
$var reg 1 $ s1 $end
$var reg 1 % s2 $end
$scope module func $end
$var wire 8 & d [7:0] $end
$var wire 1 # s0 $end
$var wire 1 $ s1 $end
$var wire 1 % s2 $end
$var reg 1 ! f $end
$upscope $end
$upscope $end
$enddefinitions $end
#0
$dumpvars
b0 &
0%
0$
0#
b0 "
0!
$end
#20
1!
b1 "
b1 &
#40
0!
1#
b10 "
b10 &
#60
1!
1$
0#
b100 "
b100 &
#80
0!
1#
b1000 "
b1000 &
#100
1%
0$
0#
b10000 "
b10000 &
#120
1!
1#
b100000 "
b100000 &
#140
0!
1$
0#
b1000000 "
b1000000 &
#160
1!
1#
b10000000 "
b10000000 &
