Lab_8/ex2.v
module ex2(clk, reset, x, state);
  input clk, reset, x;
  output reg [1:0] state;
  reg [1:0] next_state;

  // T Flip-Flop behavior
  always @(posedge clk or posedge reset) begin
    if (reset) state <= 2'b00;
    else state <= next_state;
  end

  always @(state or x) begin
    case (state)
      2'b00: if (x) next_state = 2'b11; else next_state = 2'b01; // 00 to 11 or 01
      2'b01: if (x) next_state = 2'b10; else next_state = 2'b00; // 01 to 10 or 00
      2'b10: if (x) next_state = 2'b10; else next_state = 2'b11; // 10 to 10 or 11
      2'b11: if (x) next_state = 2'b01; else next_state = 2'b00; // 11 to 01 or 00
      default: next_state = 2'b00; // default reset state
    endcase
  end
endmodule

Lab_8/ex2_tb.v
`timescale 1ns/1ns
`include "ex2.v"
module ex2_tb();
  reg clk, reset, x;
  wire [1:0] state;
  
ex2 uut (clk, reset, x, state);

  initial clk = 0;
  always #10 clk = ~clk;

  initial begin
    $dumpfile("ex2_tb.vcd");
    $dumpvars(0, ex2_tb);
    reset = 1; x = 0;
    #20 reset = 0; x = 1; #20;
    x = 0; #20;
    x = 1; #20;
    x = 0; #20;
    x = 1; #20;
    x = 0; #20;
    $display("Test Complete");
    $finish;
  end
endmodule

Lab_8/ex2_tb.vcd
$date
	Wed Oct  9 09:32:09 2024
$end
$version
	Icarus Verilog
$end
$timescale
	1ns
$end
$scope module ex2_tb $end
$var wire 2 ! state [1:0] $end
$var reg 1 " clk $end
$var reg 1 # reset $end
$var reg 1 $ x $end
$scope module uut $end
$var wire 1 " clk $end
$var wire 1 # reset $end
$var wire 1 $ x $end
$var reg 2 % next_state [1:0] $end
$var reg 2 & state [1:0] $end
$upscope $end
$upscope $end
$enddefinitions $end
#0
$dumpvars
b0 &
b1 %
0$
1#
0"
b0 !
$end
#10
1"
#20
b11 %
0"
1$
0#
#30
b1 %
b11 !
b11 &
1"
#40
b0 %
0"
0$
#50
b1 %
b0 !
b0 &
1"
#60
b11 %
0"
1$
#70
b1 %
b11 !
b11 &
1"
#80
b0 %
0"
0$
#90
b1 %
b0 !
b0 &
1"
#100
b11 %
0"
1$
#110
b1 %
b11 !
b11 &
1"
#120
b0 %
0"
0$
#130
b1 %
b0 !
b0 &
1"
