Lab_8/q1.v
module q1(x, clk, reset, state, out);
  input x, clk, reset;
  output reg [2:0] state;
  output reg out;
  reg [2:0] next_state;

  always @(posedge clk or posedge reset) begin
    if (reset) state <= 3'b000;
    else state <= next_state;
  end

  always @(state or x) begin
    case (state)
      3'b000: if (x) next_state = 3'b001; else next_state = 3'b101;
      3'b001: if (x) next_state = 3'b011; else next_state = 3'b010;
      3'b010: if (x) next_state = 3'b100; else next_state = 3'b101;
      3'b011: if (x) next_state = 3'b000; else next_state = 3'b110;
      3'b100: if (x) next_state = 3'b111; else next_state = 3'b011;
      3'b101: if (x) next_state = 3'b001; else next_state = 3'b101;
      3'b110: if (x) next_state = 3'b111; else next_state = 3'b110;
      3'b111: if (x) next_state = 3'b000; else next_state = 3'b011;
    endcase
    out = (state == 3'b011 || state == 3'b100 || state == 3'b101 || state == 3'b111);
  end
endmodule

Lab_8/q1_tb.v
`timescale 1ns/1ns
`include "q1.v"
module q1_tb();
  reg x, clk, reset;
  wire [2:0] state;
  wire out;
 q1 uut (x, clk, reset, state, out);

  initial clk = 0;
  always #10 clk = ~clk;

  initial begin
    $dumpfile("q1_tb.vcd");
    $dumpvars(0, q1_tb);
    reset = 1; x = 0;
    #20 reset = 0; x = 1;
    #20 x = 0;
    #20 x = 1;
    #20 x = 0;
    #20 x = 1;
    #20 
$display("Test Complete");    
$finish;
  end
endmodule

Lab_8/q1_tb.vcd
$date
	Wed Oct  9 09:27:42 2024
$end
$version
	Icarus Verilog
$end
$timescale
	1ns
$end
$scope module q1_tb $end
$var wire 3 ! state [2:0] $end
$var wire 1 " out $end
$var reg 1 # clk $end
$var reg 1 $ reset $end
$var reg 1 % x $end
$scope module uut $end
$var wire 1 # clk $end
$var wire 1 $ reset $end
$var wire 1 % x $end
$var reg 3 & next_state [2:0] $end
$var reg 1 " out $end
$var reg 3 ' state [2:0] $end
$upscope $end
$upscope $end
$enddefinitions $end
#0
$dumpvars
b0 '
b101 &
0%
1$
0#
0"
b0 !
$end
#10
1#
#20
b1 &
0#
1%
0$
#30
b11 &
b1 !
b1 '
1#
#40
b10 &
0#
0%
#50
b101 &
b10 !
b10 '
1#
#60
b100 &
0#
1%
#70
1"
b111 &
b100 !
b100 '
1#
#80
b11 &
0#
0%
#90
b110 &
b11 !
b11 '
1#
#100
b0 &
0#
1%
#110
0"
b1 &
b0 !
b0 '
1#
