Lab_5/mux4to1.v
module mux4to1(w1,w2,w3,w4,s1,s2,f);
input w1,w2,w3,w4,s1,s2;
output f;
reg f;

always @(w1 or w2 or w3 or w4 or s1 or s2)
begin
	if(s1==0 && s2==0) 
	begin
	f=w1;
	end
	
	if(s1==0 && s2==1)
	begin
	f=w2;
	end
	
	if(s1==1 && s2==0)
	begin
	f=w3;
	end
	
	if(s1==1 && s2==1)
	begin
	f=w4;
	end
end
endmodule

Lab_5/q1.v
`include "mux4to1.v"
module q1(a,b,c,d,f);
input a,b,c,d;
output f;
wire i0,i1,i2,i3;

assign io=(~(c & d));
assign i1=(~d);
assign i2=(~c&d);
assign i3=(~d);

mux4to1 func(i0,i1,i2,i3,a,b,f);

endmodule

Lab_5/q1_tb.v
`timescale 1ns/1ns
`include "q1.v"

module q1_tb();

reg io,i1,i2,i3,a,b;
wire f;

integer i;

q1 hey(a,b,c,d,f);

initial
begin

$dumpfile("q1_tb.vcd");
	$dumpvars(0,q1_tb);
	
for(i=0;i<64;i=i+1) 
begin
{a,b,io,i1,i2,i3}=i;#20;
end

	$display("Test Complete");
	
end
endmodule

Lab_5/q1_tb.vcd
$date
	Wed Aug 28 10:02:59 2024
$end
$version
	Icarus Verilog
$end
$timescale
	1ns
$end
$scope module q1_tb $end
$var wire 1 ! c $end
$var wire 1 " d $end
$var wire 1 # f $end
$var reg 1 $ a $end
$var reg 1 % b $end
$var reg 1 & i1 $end
$var reg 1 ' i2 $end
$var reg 1 ( i3 $end
$var reg 1 ) io $end
$var integer 32 * i [31:0] $end
$scope module hey $end
$var wire 1 $ a $end
$var wire 1 % b $end
$var wire 1 ! c $end
$var wire 1 " d $end
$var wire 1 + i0 $end
$var wire 1 , i1 $end
$var wire 1 - i2 $end
$var wire 1 . i3 $end
$var wire 1 / io $end
$var wire 1 # f $end
$scope module func $end
$var wire 1 $ s1 $end
$var wire 1 % s2 $end
$var wire 1 + w1 $end
$var wire 1 , w2 $end
$var wire 1 - w3 $end
$var wire 1 . w4 $end
$var reg 1 # f $end
$upscope $end
$upscope $end
$upscope $end
$enddefinitions $end
#0
$dumpvars
x/
z.
x-
z,
z+
b0 *
0)
0(
0'
0&
0%
0$
z#
z"
z!
$end
#20
1(
b1 *
#40
1'
0(
b10 *
#60
1(
b11 *
#80
1&
0'
0(
b100 *
#100
1(
b101 *
#120
1'
0(
b110 *
#140
1(
b111 *
#160
1)
0&
0'
0(
b1000 *
#180
1(
b1001 *
#200
1'
0(
b1010 *
#220
1(
b1011 *
#240
1&
0'
0(
b1100 *
#260
1(
b1101 *
#280
1'
0(
b1110 *
#300
1(
b1111 *
#320
1%
0)
0&
0'
0(
b10000 *
#340
1(
b10001 *
#360
1'
0(
b10010 *
#380
1(
b10011 *
#400
1&
0'
0(
b10100 *
#420
1(
b10101 *
#440
1'
0(
b10110 *
#460
1(
b10111 *
#480
1)
0&
0'
0(
b11000 *
#500
1(
b11001 *
#520
1'
0(
b11010 *
#540
1(
b11011 *
#560
1&
0'
0(
b11100 *
#580
1(
b11101 *
#600
1'
0(
b11110 *
#620
1(
b11111 *
#640
x#
1$
0%
0)
0&
0'
0(
b100000 *
#660
1(
b100001 *
#680
1'
0(
b100010 *
#700
1(
b100011 *
#720
1&
0'
0(
b100100 *
#740
1(
b100101 *
#760
1'
0(
b100110 *
#780
1(
b100111 *
#800
1)
0&
0'
0(
b101000 *
#820
1(
b101001 *
#840
1'
0(
b101010 *
#860
1(
b101011 *
#880
1&
0'
0(
b101100 *
#900
1(
b101101 *
#920
1'
0(
b101110 *
#940
1(
b101111 *
#960
z#
1%
0)
0&
0'
0(
b110000 *
#980
1(
b110001 *
#1000
1'
0(
b110010 *
#1020
1(
b110011 *
#1040
1&
0'
0(
b110100 *
#1060
1(
b110101 *
#1080
1'
0(
b110110 *
#1100
1(
b110111 *
#1120
1)
0&
0'
0(
b111000 *
#1140
1(
b111001 *
#1160
1'
0(
b111010 *
#1180
1(
b111011 *
#1200
1&
0'
0(
b111100 *
#1220
1(
b111101 *
#1240
1'
0(
b111110 *
#1260
1(
b111111 *
#1280
b1000000 *
