Lab_2/q1.v
module q1(a,b,c,d,f);
input a,b,c,d;
output f;

wire g,h;
assign g=(a&b);
assign h=(c|d);

assign f=(~h&(~g))|(g&h);

endmodule

Lab_2/q1_tb.v
`timescale 1ns/1ns
`include "q1.v"

module q1_tb();
reg a,b,c,d;
wire f;

q1 hmm(a,b,c,d,f);

initial
begin

	$dumpfile("q1_tb.vcd");
	$dumpvars(0,q1_tb);
	
a=1'b0; b=1'b0; c=1'b0; d=1'b0;
#20;
a=1'b0; b=1'b0; c=1'b0; d=1'b1;
#20;
a=1'b0; b=1'b0; c=1'b1; d=1'b0;
#20;
a=1'b0; b=1'b1; c=1'b0; d=1'b0;
#20;
a=1'b1; b=1'b0; c=1'b0; d=1'b0;
#20;
a=1'b0; b=1'b0; c=1'b1; d=1'b1;
#20;
a=1'b0; b=1'b1; c=1'b1; d=1'b0;
#20;
a=1'b1; b=1'b1; c=1'b0; d=1'b0;
#20;
a=1'b1; b=1'b0; c=1'b1; d=1'b0;
#20;
a=1'b0; b=1'b1; c=1'b0; d=1'b1;
#20;
a=1'b0; b=1'b1; c=1'b1; d=1'b1;
#20;
a=1'b1; b=1'b1; c=1'b1; d=1'b0;
#20;
a=1'b1; b=1'b0; c=1'b1; d=1'b1;
#20;
a=1'b1; b=1'b1; c=1'b0; d=1'b1;
#20;
a=1'b1; b=1'b1; c=1'b1; d=1'b1;
#20;

	$display("Test Complete");
end
endmodule

Lab_2/q1_tb.vcd
$date
	Wed Aug  7 10:14:50 2024
$end
$version
	Icarus Verilog
$end
$timescale
	1ns
$end
$scope module q1_tb $end
$var wire 1 ! f $end
$var reg 1 " a $end
$var reg 1 # b $end
$var reg 1 $ c $end
$var reg 1 % d $end
$scope module hmm $end
$var wire 1 " a $end
$var wire 1 # b $end
$var wire 1 $ c $end
$var wire 1 % d $end
$var wire 1 ! f $end
$var wire 1 & g $end
$var wire 1 ' h $end
$upscope $end
$upscope $end
$enddefinitions $end
#0
$dumpvars
0'
0&
0%
0$
0#
0"
1!
$end
#20
0!
1'
1%
#40
0%
1$
#60
1!
0'
0$
1#
#80
0#
1"
#100
0!
1'
1%
1$
0"
#120
0%
1#
#140
0'
1&
0$
1"
#160
1'
0&
1$
0#
#180
1%
0$
1#
0"
#200
1$
#220
1!
1&
0%
1"
#240
0!
0&
1%
0#
#260
1!
1&
0$
1#
#280
1$
