Lab_2/q2.v
module q2(a,b,cin,s,co);
input a,b,cin;
output s,co;

assign s=(a^b^cin);
assign co=(b&(a^cin))|(a&cin);

endmodule

Lab_2/q2_tb.v
`timescale 1ns/1ns
`include "q2.v"

module q2_tb();

reg a,b,cin;
wire s,co;

q2 hola(a,b,cin,s,co);

initial
begin

	$dumpfile("q2_tb.vcd");
	$dumpvars(0,q2_tb);
	
a=1'b0;b=1'b0;cin=1'b0;
#20;
a=1'b0;b=1'b0;cin=1'b1;
#20;
a=1'b0;b=1'b1;cin=1'b0;
#20;
a=1'b1;b=1'b0;cin=1'b0;
#20;
a=1'b0;b=1'b1;cin=1'b1;
#20;
a=1'b1;b=1'b0;cin=1'b1;
#20;
a=1'b1;b=1'b1;cin=1'b0;
#20;
a=1'b1;b=1'b1;cin=1'b1;
#20;

	$display("Test Complete");
	
end 
endmodule

Lab_2/q2_tb.vcd
$date
	Wed Aug  7 10:40:46 2024
$end
$version
	Icarus Verilog
$end
$timescale
	1ns
$end
$scope module q2_tb $end
$var wire 1 ! s $end
$var wire 1 " co $end
$var reg 1 # a $end
$var reg 1 $ b $end
$var reg 1 % cin $end
$scope module hola $end
$var wire 1 # a $end
$var wire 1 $ b $end
$var wire 1 % cin $end
$var wire 1 " co $end
$var wire 1 ! s $end
$upscope $end
$upscope $end
$enddefinitions $end
#0
$dumpvars
0%
0$
0#
0"
0!
$end
#20
1!
1%
#40
0"
0%
1$
#60
0$
1#
#80
1"
0!
1%
1$
0#
#100
0$
1#
#120
1"
0%
1$
#140
1!
1%
