week_2/Q1.v
module Q1 (a,b,c,d,f);
input a,b,c,d;
output f;
assign f=(((~a)&(~b))|((~c)&(~d))|(a&(~b)&(~c)));
endmodule

week_2/Q1_tb.v
`timescale 1ns/1ns
`include "Q1.v"

module Q1_tb();
reg a,b,c,d;
wire f;

Q1 hi(a,b,c,d,f);
initial
begin
	$dumpfile("Q1_tb.vcd");
	$dumpvars(0,Q1_tb);


a=1'b0; b=1'b0; c=1'b0; d=1'b0;
#20;

a=1'b0; b=1'b0; c=1'b0; d=1'b1;
#20;

a=1'b0; b=1'b0; c=1'b1; d=1'b0;
#20;

a=1'b0; b=1'b1; c=1'b0; d=1'b0;
#20;

a=1'b1; b=1'b0; c=1'b0; d=1'b0;
#20;

a=1'b0; b=1'b0; c=1'b1; d=1'b1;
#20;

a=1'b0; b=1'b1; c=1'b1; d=1'b0;
#20;

a=1'b1; b=1'b1; c=1'b0; d=1'b0;
#20;

a=1'b1; b=1'b0; c=1'b0; d=1'b1;
#20;

a=1'b0; b=1'b1; c=1'b0; d=1'b1;
#20;

a=1'b0; b=1'b1; c=1'b1; d=1'b1;
#20;

a=1'b1; b=1'b1; c=1'b0; d=1'b1;
#20;

a=1'b1; b=1'b1; c=1'b1; d=1'b1;
#20;

a=1'b1; b=1'b0; c=1'b1; d=1'b1;
#20;

a=1'b1; b=1'b1; c=1'b1; d=1'b0;
#20;

a=1'b1; b=1'b0; c=1'b1; d=1'b0;
#20;

	$display("Test Complete");
	
end
endmodule

week_2/Q1_tb.vcd
$date
	Wed Jul 31 10:24:24 2024
$end
$version
	Icarus Verilog
$end
$timescale
	1ns
$end
$scope module Q1_tb $end
$var wire 1 ! f $end
$var reg 1 " a $end
$var reg 1 # b $end
$var reg 1 $ c $end
$var reg 1 % d $end
$scope module hi $end
$var wire 1 " a $end
$var wire 1 # b $end
$var wire 1 $ c $end
$var wire 1 % d $end
$var wire 1 ! f $end
$upscope $end
$upscope $end
$enddefinitions $end
#0
$dumpvars
0%
0$
0#
0"
1!
$end
#20
1%
#40
0%
1$
#60
0$
1#
#80
0#
1"
#100
1%
1$
0"
#120
0!
0%
1#
#140
1!
0$
1"
#160
1%
0#
#180
0!
1#
0"
#200
1$
#220
0$
1"
#240
1$
#260
0#
#280
0%
1#
#300
0#
