week_2/Q1b.v
module Q1b(a,b,c,d,f);
input a,b,c,d;
output f;
assign f=(~a&(~c)&(~d))|(a&b&(~c))|(c&(~d))|(~a&b&c);
endmodule

week_2/Q1b_tb.v
`timescale 1ns/1ns
`include "Q1b.v"

module Q1b_tb();
reg a,b,c,d;
wire f;

Q1b hi(a,b,c,d,f);

initial
begin

	$dumpfile("Q1b_tb.vcd");
	$dumpvars(0,Q1b_tb);
	
a=1'b0; b=1'b0; c=1'b0; d=1'b0;
#20;

a=1'b0; b=1'b0; c=1'b0; d=1'b1;
#20;

a=1'b0; b=1'b0; c=1'b1; d=1'b0;
#20;

a=1'b0; b=1'b1; c=1'b0; d=1'b0;
#20;

a=1'b1; b=1'b0; c=1'b0; d=1'b0;
#20;

a=1'b0; b=1'b0; c=1'b1; d=1'b1;
#20;

a=1'b0; b=1'b1; c=1'b1; d=1'b0;
#20;

a=1'b1; b=1'b1; c=1'b0; d=1'b0;
#20;

a=1'b1; b=1'b0; c=1'b0; d=1'b1;
#20;

a=1'b0; b=1'b1; c=1'b0; d=1'b1;
#20;

a=1'b0; b=1'b1; c=1'b1; d=1'b1;
#20;

a=1'b1; b=1'b1; c=1'b0; d=1'b1;
#20;

a=1'b1; b=1'b1; c=1'b1; d=1'b1;
#20;

a=1'b1; b=1'b0; c=1'b1; d=1'b1;
#20;

a=1'b1; b=1'b1; c=1'b1; d=1'b0;
#20;

a=1'b1; b=1'b0; c=1'b1; d=1'b0;
#20;

	$display("Test Complete");
	
end
endmodule

week_2/Q1b_tb.vcd
$date
	Wed Jul 31 10:55:02 2024
$end
$version
	Icarus Verilog
$end
$timescale
	1ns
$end
$scope module Q1b_tb $end
$var wire 1 ! f $end
$var reg 1 " a $end
$var reg 1 # b $end
$var reg 1 $ c $end
$var reg 1 % d $end
$scope module hi $end
$var wire 1 " a $end
$var wire 1 # b $end
$var wire 1 $ c $end
$var wire 1 % d $end
$var wire 1 ! f $end
$upscope $end
$upscope $end
$enddefinitions $end
#0
$dumpvars
0%
0$
0#
0"
1!
$end
#20
0!
1%
#40
1!
0%
1$
#60
1!
0$
1#
#80
0!
0#
1"
#100
0!
1%
1$
0"
#120
1!
0%
1#
#140
1!
0$
1"
#160
0!
1%
0#
#180
1#
0"
#200
1!
1$
#220
1!
0$
1"
#240
0!
1$
#260
0#
#280
1!
0%
1#
#300
0#
